{
  "name": "CommandLine",
  "plural": "commandLines",
  "base": "PersistedModel",
  "idInjection": true,
  "options": {
    "validateUpsert": true
  },
  "properties": {
    "quantity": {
      "type": "number",
      "required": true,
      "default": 0
    },
    "price": {
      "type": "number",
      "default": 0
    }
  },
  "validations": [],
  "relations": {
    "article": {
      "type": "belongsTo",
      "model": "Product",
      "foreignKey": "",
      "options": {
        "nestRemoting": true,
        "disableInclude": true
      }
    }
  },
  "acls": [],
  "methods": {}
}
